nodeconductor_azure/__init__.py
nodeconductor_azure/admin.py
nodeconductor_azure/apps.py
nodeconductor_azure/backend.py
nodeconductor_azure/cost_tracking.py
nodeconductor_azure/driver.py
nodeconductor_azure/executors.py
nodeconductor_azure/extension.py
nodeconductor_azure/filters.py
nodeconductor_azure/handlers.py
nodeconductor_azure/models.py
nodeconductor_azure/serializers.py
nodeconductor_azure/tasks.py
nodeconductor_azure/urls.py
nodeconductor_azure/views.py
nodeconductor_azure/migrations/0001_initial.py
nodeconductor_azure/migrations/__init__.py
nodeconductor_azure/tests/__init__.py
nodeconductor_azure/tests/factories.py
nodeconductor_azure/tests/fixtures.py
nodeconductor_azure/tests/test_driver.py
nodeconductor_azure/tests/test_virtual_machines.py
nodeconductor_azure/tests/unittests/__init__.py
nodeconductor_azure/tests/unittests/test_handlers.py
nodeconductor_azure-0.2.0.dist-info/DESCRIPTION.rst
nodeconductor_azure-0.2.0.dist-info/METADATA
nodeconductor_azure-0.2.0.dist-info/RECORD
nodeconductor_azure-0.2.0.dist-info/WHEEL
nodeconductor_azure-0.2.0.dist-info/entry_points.txt
nodeconductor_azure-0.2.0.dist-info/metadata.json
nodeconductor_azure-0.2.0.dist-info/top_level.txt
