Metadata-Version: 2.0
Name: nodeconductor-azure
Version: 0.2.0
Summary: Waldur plugin for managing MS Azure resources.
Home-page: https://waldur.com
Author: OpenNode Team
Author-email: info@opennodecloud.com
License: MIT
Platform: UNKNOWN
Classifier: Framework :: Django
Classifier: Intended Audience :: Developers
Classifier: Intended Audience :: System Administrators
Classifier: Operating System :: OS Independent
Classifier: License :: OSI Approved :: MIT License
Requires-Dist: apache-libcloud (>=1.1.0,<2.2.0)
Requires-Dist: cryptography
Requires-Dist: nodeconductor (>0.139.0)
Provides-Extra: dev
Requires-Dist: Sphinx (==1.2.2); extra == 'dev'
